udax/__init__.py
udax/algorithm.py
udax/cli.py
udax/csv.py
udax/fn.py
udax/pagerank.py
udax/rouge.py
udax/statistics.py
udax/string.py
udax/textrank.py
udax/dataset/__init__.py
udax/dataset/glove.py
udax-0.0.5.dist-info/LICENSE
udax-0.0.5.dist-info/METADATA
udax-0.0.5.dist-info/WHEEL
udax-0.0.5.dist-info/top_level.txt
udax-0.0.5.dist-info/RECORD
